aihub/__init__.py
aihub/client.py
aihub/exceptions.py
aihub/cli/__init__.py
aihub/cli/__main__.py
aihub/cli/config.py
aihub/cli/main.py
aihub/cli/model_center.py
aihub/models/__init__.py
aihub/models/artifact.py
aihub/models/common.py
aihub/models/data_warehouse.py
aihub/models/dataset_management.py
aihub/models/document_center.py
aihub/models/eval.py
aihub/models/labelfree.py
aihub/models/model_center.py
aihub/models/model_deployment.py
aihub/models/model_training_platform.py
aihub/models/notebook_management.py
aihub/models/quota_schedule_management.py
aihub/models/tag_resource_management.py
aihub/models/task_center.py
aihub/models/user_system.py
aihub/models/workflow_center.py
aihub/services/__init__.py
aihub/services/artifact.py
aihub/services/data_warehouse.py
aihub/services/dataset_management.py
aihub/services/document_center.py
aihub/services/eval.py
aihub/services/labelfree.py
aihub/services/model_center.py
aihub/services/model_deployment.py
aihub/services/model_training_platform.py
aihub/services/notebook_management.py
aihub/services/quota_schedule_management.py
aihub/services/reporter.py
aihub/services/tag_resource_management.py
aihub/services/task_center.py
aihub/services/user_system.py
aihub/services/workflow_center.py
aihub/utils/__init__.py
aihub/utils/di.py
aihub/utils/download.py
aihub/utils/http.py
aihub/utils/s3.py
intellif_aihub-0.1.54.dist-info/licenses/LICENSE
intellif_aihub-0.1.54.dist-info/METADATA
intellif_aihub-0.1.54.dist-info/WHEEL
intellif_aihub-0.1.54.dist-info/entry_points.txt
intellif_aihub-0.1.54.dist-info/top_level.txt
intellif_aihub-0.1.54.dist-info/RECORD
