Metadata-Version: 2.4
Name: intellif-aihub
Version: 0.1.54
Summary: Intellif AI-hub SDK.
Author-email: Platform Team <aihub@example.com>
License-Expression: Apache-2.0
Keywords: AI-hub,sdk,intellif
Classifier: Programming Language :: Python :: 3
Classifier: Operating System :: OS Independent
Requires-Python: >=3.9
License-File: LICENSE
Requires-Dist: httpx>=0.27
Requires-Dist: pydantic<3.0,>=2.5.3
Requires-Dist: typing-extensions<5.0,>=4.13.2
Requires-Dist: pyarrow>=21.0.0
Requires-Dist: tqdm<5.0,>=4.66
Requires-Dist: loguru>=0.7.3
Requires-Dist: minio==7.2.7
Requires-Dist: requests>=2.32.4
Requires-Dist: typer>=0.12.0
Dynamic: license-file
